feature_pipeline/__init__.py
feature_pipeline/clean_feature_store.py
feature_pipeline/decorator_singleton_mixin_design_patterns.py
feature_pipeline/etl/__init__.py
feature_pipeline/etl/cleaning.py
feature_pipeline/etl/extract.py
feature_pipeline/etl/load.py
feature_pipeline/etl/validation.py
feature_pipeline/feature_view.py
feature_pipeline/pipeline.py
feature_pipeline/settings.py
feature_pipeline/utils.py
feature_pipeline-0.1.0.dist-info/METADATA
feature_pipeline-0.1.0.dist-info/WHEEL
feature_pipeline-0.1.0.dist-info/RECORD
