Metadata-Version: 2.1
Name: feature-pipeline
Version: 0.1.0
Summary: 
Author: Iusztin Paul
Author-email: p.e.iusztin@gmail.com
Requires-Python: >=3.9,<3.10
Classifier: Programming Language :: Python :: 3
Classifier: Programming Language :: Python :: 3.9
Requires-Dist: fire (>=0.5.0,<0.6.0)
Requires-Dist: hopsworks (==3.4.3)
Requires-Dist: pandas (>=1.3.5)
Requires-Dist: python-dotenv (>=0.21.1)
Requires-Dist: requests (>=2.28.2,<3.0.0)
Requires-Dist: yarl (>=1.8.2,<2.0.0)
